raypack/__init__.py
raypack/__main__.py
raypack/aws_interface.py
raypack/build.py
raypack/config_loading.py
raypack/logging_utils.py
raypack/poetry_interface.py
raypack/pyproject_interface.py
raypack/setuptools_interface.py
raypack-0.4.0.dist-info/LICENSE
raypack-0.4.0.dist-info/METADATA
raypack-0.4.0.dist-info/WHEEL
raypack-0.4.0.dist-info/entry_points.txt
raypack-0.4.0.dist-info/RECORD
