Metadata-Version: 2.1
Name: raypack
Version: 0.4.0
Summary: Unofficial AWS Glue Ray.io packaging tool. Pure python or cross platform.
Home-page: https://github.com/matthewdeanmartin/raypack
License: MIT
Keywords: awsglue,ray.io,aws glue
Author: Matthew Martin
Author-email: matthewdeanmartin@gmail.com
Requires-Python: >=3.9,<4.0
Classifier: Development Status :: 3 - Alpha
Classifier: Intended Audience :: Developers
Classifier: License :: OSI Approved :: MIT License
Classifier: Operating System :: OS Independent
Classifier: Programming Language :: Python
Classifier: Programming Language :: Python :: 3
Classifier: Programming Language :: Python :: 3.9
Classifier: Programming Language :: Python :: 3.10
Classifier: Programming Language :: Python :: 3.11
Classifier: Programming Language :: Python :: 3.12
Requires-Dist: boto3 (>=1.28.71)
Requires-Dist: poetry (>=1.6.1)
Requires-Dist: toml (>=0.10.2)
Project-URL: Bug Tracker, https://github.com/matthewdeanmartin/raypack/issues
Project-URL: Change Log, https://github.com/matthewdeanmartin/raypack/blob/main/CHANGES.md
Project-URL: Documentation, https://github.com/matthewdeanmartin/raypack
Project-URL: Repository, https://github.com/matthewdeanmartin/raypack
